textfier/__init__.py
textfier/core/__init__.py
textfier/core/dataset.py
textfier/core/runner.py
textfier/core/task.py
textfier/stream/__init__.py
textfier/stream/cleaner.py
textfier/stream/tokenizer.py
textfier/tasks/__init__.py
textfier/tasks/language_modeling.py
textfier/tasks/named_entity_recognition.py
textfier/tasks/question_answering.py
textfier/tasks/seq2seq.py
textfier/tasks/sequence_classification.py
textfier/utils/__init__.py
textfier/utils/loader.py
textfier/utils/logging.py
textfier/utils/metrics.py
textfier-1.0.2.dist-info/LICENSE
textfier-1.0.2.dist-info/METADATA
textfier-1.0.2.dist-info/WHEEL
textfier-1.0.2.dist-info/top_level.txt
textfier-1.0.2.dist-info/RECORD
