Metadata-Version: 2.1
Name: textfier
Version: 1.0.2
Summary: Text-based Modifiers
Home-page: https://github.com/gugarosa/textfier
Author: Gustavo Rosa
Author-email: gustavo.rosa@unesp.br
License: Apache 2.0
Platform: UNKNOWN
Classifier: Development Status :: 5 - Production/Stable
Classifier: Intended Audience :: Developers
Classifier: Intended Audience :: Education
Classifier: Intended Audience :: Science/Research
Classifier: License :: OSI Approved :: Apache Software License
Classifier: Programming Language :: Python :: 3.6
Classifier: Programming Language :: Python :: 3.7
Classifier: Programming Language :: Python :: 3.8
Classifier: Programming Language :: Python :: 3.9
Classifier: Topic :: Software Development :: Libraries
Classifier: Topic :: Software Development :: Libraries :: Python Modules
License-File: LICENSE
Requires-Dist: coverage (>=5.5)
Requires-Dist: nltk (>=3.5)
Requires-Dist: pandas (>=1.2.3)
Requires-Dist: pre-commit (>=2.17.0)
Requires-Dist: pylint (>=2.7.2)
Requires-Dist: pytest (>=6.2.2)
Requires-Dist: scikit-learn (>=0.24.1)
Requires-Dist: transformers (>=4.3.3)
Provides-Extra: tests
Requires-Dist: coverage ; extra == 'tests'
Requires-Dist: pytest ; extra == 'tests'
Requires-Dist: pytest-pep8 ; extra == 'tests'
